ImbBag/ADASYNBag.py
ImbBag/BBag.py
ImbBag/BEBS.py
ImbBag/BEV.py
ImbBag/CostBag.py
ImbBag/EBBag.py
ImbBag/EUSBag.py
ImbBag/ImbalanceBaggingClassifier.py
ImbBag/LazyBag.py
ImbBag/MRBBag.py
ImbBag/Measures.py
ImbBag/Metrics.py
ImbBag/MultiRandBalBag.py
ImbBag/NBBag.py
ImbBag/OverBag.py
ImbBag/PTBag.py
ImbBag/RBBag.py
ImbBag/RBSBag.py
ImbBag/REABag.py
ImbBag/RSYNBag.py
ImbBag/SMOTEBag.py
ImbBag/UnderBag.py
ImbBag/UnderBagKNN.py
ImbBag/__init__.py
ImbBag/interface.py
ImbBag/utils.py
imbbag-1.3.dist-info/licenses/LICENSE.txt
imbbag-1.3.dist-info/METADATA
imbbag-1.3.dist-info/WHEEL
imbbag-1.3.dist-info/top_level.txt
imbbag-1.3.dist-info/RECORD
