Metadata-Version: 2.4
Name: imbbag
Version: 1.3
Summary: Package contains a collection of bagging ensemble algorithms for imbalanced data classification
Home-page: https://github.com/yousefabdi/imbbag
Author: Yousef Abdi
Author-email: yousef.abdi@gmail.com
Classifier: License :: OSI Approved :: MIT License
Classifier: Programming Language :: Python
Classifier: Programming Language :: Python :: 3.11
License-File: LICENSE.txt
Requires-Dist: scikit-learn
Requires-Dist: patch_sklearn
Requires-Dist: imblearn
Requires-Dist: numpy
Requires-Dist: scipy
Requires-Dist: PyGAD
Requires-Dist: mlxtend
Requires-Dist: scikit-learn-intelex
Requires-Dist: ARFS
Dynamic: author
Dynamic: author-email
Dynamic: classifier
Dynamic: description
Dynamic: description-content-type
Dynamic: home-page
Dynamic: license-file
Dynamic: requires-dist
Dynamic: summary
